openfaas_lambda_utils/__init__.py
openfaas_lambda_utils/py.typed
openfaas_lambda_utils/stats.py
openfaas_lambda_utils/streaming.py
openfaas_lambda_utils/types.py
openfaas_lambda_utils-0.1.3.dist-info/LICENSE.txt
openfaas_lambda_utils-0.1.3.dist-info/METADATA
openfaas_lambda_utils-0.1.3.dist-info/WHEEL
openfaas_lambda_utils-0.1.3.dist-info/top_level.txt
openfaas_lambda_utils-0.1.3.dist-info/RECORD
